trajectory/__init__.py
trajectory/clients.py
trajectory/constants.py
trajectory/evaluation_run.py
trajectory/rules.py
trajectory/run_evaluation.py
trajectory/trajectory_client.py
trajectory/version_check.py
trajectory/cli/__init__.py
trajectory/cli/traj.py
trajectory/common/__init__.py
trajectory/common/constants.py
trajectory/common/exceptions.py
trajectory/common/local_trace_storage.py
trajectory/common/logger.py
trajectory/common/utils.py
trajectory/common/api/__init__.py
trajectory/common/api/api.py
trajectory/common/api/constants.py
trajectory/common/storage/__init__.py
trajectory/common/storage/s3_storage.py
trajectory/common/tracer/__init__.py
trajectory/common/tracer/constants.py
trajectory/common/tracer/core.py
trajectory/common/tracer/otel_exporter.py
trajectory/common/tracer/otel_span_processor.py
trajectory/common/tracer/span_processor.py
trajectory/common/tracer/span_transformer.py
trajectory/common/tracer/trace_manager.py
trajectory/data/__init__.py
trajectory/data/example.py
trajectory/data/result.py
trajectory/data/scorer_data.py
trajectory/data/tool.py
trajectory/data/trace.py
trajectory/data/trace_run.py
trajectory/data/trajectory_types.py
trajectory/data/datasets/__init__.py
trajectory/data/datasets/dataset.py
trajectory/data/datasets/eval_dataset_client.py
trajectory/data/scripts/fix_default_factory.py
trajectory/data/scripts/openapi_transform.py
trajectory/evaluations/__init__.py
trajectory/evaluations/base_evaluation.py
trajectory/evaluations/config_loader.py
trajectory/integrations/langgraph.py
trajectory/judges/__init__.py
trajectory/judges/base_judge.py
trajectory/judges/litellm_judge.py
trajectory/judges/mixture_of_judges.py
trajectory/judges/together_judge.py
trajectory/judges/utils.py
trajectory/scorers/__init__.py
trajectory/scorers/agent_scorer.py
trajectory/scorers/api_scorer.py
trajectory/scorers/base_scorer.py
trajectory/scorers/example_scorer.py
trajectory/scorers/exceptions.py
trajectory/scorers/score.py
trajectoryevals-0.0.7.dist-info/METADATA
trajectoryevals-0.0.7.dist-info/WHEEL
trajectoryevals-0.0.7.dist-info/entry_points.txt
trajectoryevals-0.0.7.dist-info/licenses/LICENSE.md
trajectoryevals-0.0.7.dist-info/RECORD
