Metadata-Version: 2.4
Name: trajectoryevals
Version: 0.0.7
Summary: Trajectory evals package
Author-email: Shrey Modi <shreycricket10@gmail.com>, Harsh Shah <shah.harsh2409@gmail.com>
License-Expression: Apache-2.0
License-File: LICENSE.md
Classifier: Operating System :: OS Independent
Classifier: Programming Language :: Python :: 3
Requires-Python: >=3.11
Requires-Dist: anthropic
Requires-Dist: boto3
Requires-Dist: build>=1.2.2.post1
Requires-Dist: datamodel-code-generator>=0.31.1
Requires-Dist: google-genai
Requires-Dist: langchain-anthropic
Requires-Dist: langchain-core
Requires-Dist: langchain-huggingface
Requires-Dist: langchain-openai
Requires-Dist: litellm>=1.61.15
Requires-Dist: matplotlib
Requires-Dist: nest-asyncio
Requires-Dist: openai
Requires-Dist: opentelemetry-api>=1.34.1
Requires-Dist: opentelemetry-exporter-otlp-proto-http>=1.34.1
Requires-Dist: opentelemetry-instrumentation>=0.55b1
Requires-Dist: opentelemetry-sdk>=1.34.1
Requires-Dist: pandas
Requires-Dist: python-dotenv
Requires-Dist: python-slugify>=8.0.4
Requires-Dist: requests
Requires-Dist: supabase>=2.0.0
Requires-Dist: together
Requires-Dist: twine>=6.2.0
